README
setup.py
pylogfaces.egg-info/PKG-INFO
pylogfaces.egg-info/SOURCES.txt
pylogfaces.egg-info/dependency_links.txt
pylogfaces.egg-info/top_level.txt
xmllayout/__init__.py
xmllayout/formatters.py
xmllayout/handlers.py
xmllayout/properties.py