Metadata-Version: 1.0
Name: pylogfaces
Version: 1.0.1
Summary: Logging utilities for logFaces and python.
Home-page: https://github.com/nickswebsite/pylogfaces
Author: Stojan Jovic
Author-email: send_me_spam@yahoo.com
License: UNKNOWN
Platform: UNKNOWN
